Workbook

Sheet Parametres
A1: Parametres de chiffrage - Republication automatique TikTok
A3: Legende : les cellules en BLEU sur fond JAUNE sont les seules a modifier. Tout le reste est calcule.
A5: Parametre | B5: Valeur | C5: Source / hypothese
A6: TJM (€ / jour) | B6: 400 | C6: Tarif journalier annonce oralement au client lors du premier appel
A7: Remise commerciale accordee (%) | B7: 0 | C7: Aucune remise. En cas de pression sur le prix : retirer du perimetre plutot que baisser le tarif.
A8: Taux d'acompte a la commande (%) | B8: 0.4 | C8: Usage courant en prestation de developpement : 30 a 50 %
A9: Abonnement exploitation - engagement 12 mois (€ / mois) | B9: 189 | C9: Inclut serveur, passerelle de publication, supervision, sauvegardes, maintenance corrective 1 h/mois
A10: Abonnement exploitation - sans engagement (€ / mois) | B10: 219 | C10: Majoration pour absence d'engagement de duree
A11: Taux horaire hors forfait (€ / h) | B11: 60 | C11: Interventions hors perimetre de maintenance
A12: Videos publiees par jour (communique par le client) | B12: 3 | C12: 2 a 3 videos par jour. Determine la consommation de quota YouTube et le palier de la passerelle
A13: Nombre de destinations | B13: 2 | C13: YouTube et Instagram. Facebook hors perimetre V1
A14: Cout mensuel reel serveur + passerelle (€ / mois) | B14: 75 | C14: Hypothese : VPS 15 € + passerelle de publication 60 € pour 180 publications/mois. PALIER TARIFAIRE A VERIFIER avant engagement
A15: Controle des plafonds de plateformes
A16: Consommation quota YouTube par jour (1 600 unites par envoi) | B16: =Parametres!$B$12*1600 -> 4800 | C16: Plafond par defaut : 10 000 unites/jour, soit 6 envois. Au-dela de 5 videos/jour, demande d'extension necessaire.
A17: Marge restante sur le quota YouTube | B17: =10000-B16 -> 5200
A18: Publications Instagram par jour (plafond 25 / 24 h) | B18: =Parametres!$B$12 -> 3
A19: Republications mensuelles toutes destinations | B19: =Parametres!$B$12*30*Parametres!$B$13 -> 180 | C19: Dimensionne le palier tarifaire de la passerelle de publication.
A22: Rentabilite de l'abonnement d'exploitation
A23: Marge brute mensuelle (engagement 12 mois) | B23: =Parametres!$B$9-Parametres!$B$14 -> 114
A24: Marge brute annuelle (engagement 12 mois) | B24: =B23*12 -> 1368
A25: Temps de maintenance couvert par mois (h) | B25: 1
A26: Marge nette mensuelle si le temps de maintenance inclus est consomme | B26: =B23-B25*Parametres!$B$11 -> 54 | C26: Si negatif : l'abonnement est sous-tarife, ou l'inclusion de 2 h/mois est trop genereuse.
A28: REGIME FISCAL | B28: Non assujetti a la TVA - franchise en base | C28: Mention obligatoire sur le devis et les factures : TVA non applicable, article 293 B du CGI. Ne jamais ecrire HT.

Sheet Kanban_Chiffrage
A1: Kanban de production et chiffrage detaille
A2: Colonnes Kanban : A faire > En cours > A valider (prestataire) > A valider (client) > Termine. Toutes les cartes demarrent en 'A faire'.
A3: Perimetre = Socle : figure au devis. Perimetre = Option : chiffre pour usage interne, NE FIGURE PAS au devis, a presenter en reunion de suivi.
A4: Lot | B4: Intitule du lot | C4: Carte | D4: Description de la tache | E4: Perimetre | F4: Charge (j) | G4: Montant (€) | H4: Statut Kanban
A5: LOT 0 | B5: Etude de faisabilite et cadrage technique | C5: 0.1 | D5: Prototype de detection des nouvelles publications TikTok (API officielle + repli profil public) | E5: Socle | F5: 0.5 | G5: =F5*Parametres!$B$6 -> 200 | H5: A faire
A6: LOT 0 | B6: Etude de faisabilite et cadrage technique | C6: 0.2 | D6: Prototype de recuperation automatique du fichier video - 2 methodes comparees sur 10 videos reelles | E6: Socle | F6: 0.5 | G6: =F6*Parametres!$B$6 -> 200 | H6: A faire
A7: LOT 0 | B7: Etude de faisabilite et cadrage technique | C7: 0.3 | D7: Test de publication reelle YouTube et Instagram sur comptes de test | E7: Socle | F7: 0.25 | G7: =F7*Parametres!$B$6 -> 100 | H7: A faire
A8: LOT 0 | B8: Etude de faisabilite et cadrage technique | C8: 0.4 | D8: Note de faisabilite, arbitrage d'architecture, gel du perimetre V1 | E8: Socle | F8: 0.25 | G8: =F8*Parametres!$B$6 -> 100 | H8: A faire
A9: LOT 1 | B9: Fondations techniques | C9: 1.1 | D9: Specification technique courte et modele de donnees | E9: Socle | F9: 0.25 | G9: =F9*Parametres!$B$6 -> 100 | H9: A faire
A10: LOT 1 | B10: Fondations techniques | C10: 1.2 | D10: Initialisation du projet, conteneurisation, environnements dev et prod | E10: Socle | F10: 0.25 | G10: =F10*Parametres!$B$6 -> 100 | H10: A faire
A11: LOT 1 | B11: Fondations techniques | C11: 1.3 | D11: Base de donnees et migrations (videos, publications, tentatives, comptes) | E11: Socle | F11: 0.25 | G11: =F11*Parametres!$B$6 -> 100 | H11: A faire
A12: LOT 1 | B12: Fondations techniques | C12: 1.4 | D12: Gestion securisee des secrets et jetons OAuth (chiffrement, hors code source) | E12: Socle | F12: 0.25 | G12: =F12*Parametres!$B$6 -> 100 | H12: A faire
A13: LOT 1 | B13: Fondations techniques | C13: 1.5 | D13: Journalisation structuree avec identifiant de correlation par traitement | E13: Socle | F13: 0.25 | G13: =F13*Parametres!$B$6 -> 100 | H13: A faire
A14: LOT 2 | B14: Detection des publications TikTok | C14: 2.1 | D14: Connecteur TikTok : authentification, autorisation du compte, lecture des publications | E14: Socle | F14: 0.5 | G14: =F14*Parametres!$B$6 -> 200 | H14: A faire
A15: LOT 2 | B15: Detection des publications TikTok | C15: 2.2 | D15: Planificateur de surveillance : intervalle parametrable, fenetre de rattrapage, reprise | E15: Socle | F15: 0.25 | G15: =F15*Parametres!$B$6 -> 100 | H15: A faire
A16: LOT 2 | B16: Detection des publications TikTok | C16: 2.3 | D16: Normalisation des metadonnees (id, URL, description, hashtags, duree, date, vignette) | E16: Socle | F16: 0.25 | G16: =F16*Parametres!$B$6 -> 100 | H16: A faire
... A48: LOT 10 | B48: Connecteurs natifs (alternative a la passerelle) | C48: 10.4 | D48: Renouvellement automatique des jetons longue duree et surveillance des expirations | E48: Option | F48: 1 | G48: =F48*Parametres!$B$6 -> 400 | H48: A faire
D50: TOTAL PERIMETRE SOCLE | F50: =SUMIFS(F5:F48,E5:E48,"Socle") -> 13.25 | G50: =SUMIFS(G5:G48,E5:E48,"Socle") -> 5300
D51: TOTAL OPTIONS | F51: =SUMIFS(F5:F48,E5:E48,"Option") -> 9.75 | G51: =SUMIFS(G5:G48,E5:E48,"Option") -> 3900

Sheet Devis
A1: Lignes destinees au devis client
A2: Les montants sont calcules depuis l'onglet Kanban_Chiffrage. Ne rien saisir ici.
A4: BLOC A - PRESTATION INITIALE (forfait)
A5: Ref. | B5: Libelle de la ligne de devis | C5: Detail | D5: Qte (j) | E5: P.U. (€/j) | F5: Total (€)
A6: A1 | B6: Etude de faisabilite et cadrage | C6: Validation, sur vos propres videos, de la detection et de la recuperation automatique depuis TikTok. Note de conclusion ecrite. Phase assortie d'une clause de sortie (bloc C). | D6: =SUMIFS(Kanban_Chiffrage!$F$5:$F$48,Kanban_Chiffrage!$A$5:$A$48,"LOT 0",Kanban_Chiffrage!$E$5:$E$48,"Socle") -> 1.5 | E6: =Parametres!$B$6 -> 400 | F6: =D6*E6 -> 600
A7: A2 | B7: Socle technique et detection des publications TikTok | C7: Surveillance du compte, detection des nouvelles videos, garantie qu'une video n'est traitee qu'une seule fois, exclusion des diaporamas photo, regle d'exclusion volontaire par marqueur. | D7: =SUMIFS(Kanban_Chiffrage!$F$5:$F$48,Kanban_Chiffrage!$A$5:$A$48,"LOT 1",Kanban_Chiffrage!$E$5:$E$48,"Socle")+SUMIFS(Kanban_Chiffrage!$F$5:$F$48,Kanban_Chiffrage!$A$5:$A$48,"LOT 2",Kanban_Chiffrage!$E$5:$E$48,"Socle") -> 3 | E7: =Parametres!$B$6 -> 400 | F7: =D7*E7 -> 1200
A8: A3 | B8: Recuperation automatique des videos | C8: Deux methodes de recuperation avec basculement automatique, controle de la qualite du fichier, stockage temporaire et suppression apres publication. | D8: =SUMIFS(Kanban_Chiffrage!$F$5:$F$48,Kanban_Chiffrage!$A$5:$A$48,"LOT 3",Kanban_Chiffrage!$E$5:$E$48,"Socle") -> 1.75 | E8: =Parametres!$B$6 -> 400 | F8: =D8*E8 -> 700
A9: A4 | B9: Republication automatique sur YouTube et Instagram | C9: Reprise du titre, de la description et des hashtags, adaptation aux contraintes de chaque plateforme, envoi et verification. | D9: =SUMIFS(Kanban_Chiffrage!$F$5:$F$48,Kanban_Chiffrage!$A$5:$A$48,"LOT 4",Kanban_Chiffrage!$E$5:$E$48,"Socle") -> 1.75 | E9: =Parametres!$B$6 -> 400 | F9: =D9*E9 -> 700
A10: A5 | B10: Fiabilite, reprises automatiques et alertes | C10: Nouvelles tentatives automatiques en cas d'incident, alerte par email si une publication echoue definitivement, outils de relance manuelle. | D10: =SUMIFS(Kanban_Chiffrage!$F$5:$F$48,Kanban_Chiffrage!$A$5:$A$48,"LOT 5",Kanban_Chiffrage!$E$5:$E$48,"Socle")+SUMIFS(Kanban_Chiffrage!$F$5:$F$48,Kanban_Chiffrage!$A$5:$A$48,"LOT 6",Kanban_Chiffrage!$E$5:$E$48,"Socle") -> 1.25 | E10: =Parametres!$B$6 -> 400 | F10: =D10*E10 -> 500
A11: A6 | B11: Mise en service, tests et prise en main | C11: Installation sur serveur, sauvegardes quotidiennes, tests sur videos reelles, proces-verbal de recette, session de prise en main. | D11: =SUMIFS(Kanban_Chiffrage!$F$5:$F$48,Kanban_Chiffrage!$A$5:$A$48,"LOT 7",Kanban_Chiffrage!$E$5:$E$48,"Socle")+SUMIFS(Kanban_Chiffrage!$F$5:$F$48,Kanban_Chiffrage!$A$5:$A$48,"LOT 8",Kanban_Chiffrage!$E$5:$E$48,"Socle") -> 2 | E11: =Parametres!$B$6 -> 400 | F11: =D11*E11 -> 800
A12: A7 | B12: Provision pour evolutions des plateformes | C12: Adaptation aux changements de TikTok, YouTube et Instagram pendant la phase de realisation. | D12: =SUMIFS(Kanban_Chiffrage!$F$5:$F$48,Kanban_Chiffrage!$A$5:$A$48,"LOT 9",Kanban_Chiffrage!$E$5:$E$48,"Socle") -> 2 | E12: =Parametres!$B$6 -> 400 | F12: =D12*E12 -> 800
B13: Sous-total prestation initiale | D13: =SUM(D6:D12) -> 13.25 | F13: =SUM(F6:F12) -> 5300
A14: A11 | B14: Remise commerciale accordee (le cas echeant) | C14: Levier commercial. Valeur par defaut : 0 %. En cas de pression sur le prix, retirer du perimetre plutot que baisser le tarif. | F14: =-ROUND(F13*Parametres!$B$7,-2) -> 0
B15: TOTAL PRESTATION INITIALE | F15: =F13+F14 -> 5300
A17: BLOC B - ABONNEMENT D'EXPLOITATION (obligatoire)
A18: Ref. | B18: Libelle | C18: Detail | D18: Periodicite | E18: Montant (€)
A19: B1 | B19: Formule Exploitation & Maintenance - engagement 12 mois | C19: Hebergement dedie, supervision 7 j/7, abonnement a la passerelle de publication dimensionne pour 180 republications/mois, sauvegardes quotidiennes, surveillance et renouvellement des jetons, mises a jour de securite, adaptation aux evolutions des plateformes, maintenance corrective 1 h/mois, alertes | D19: mensuel | E19: =Parametres!$B$9 -> 189
A20: B2 | B20: Variante sans engagement de duree | C20: Meme perimetre, resiliable a tout moment avec preavis d'un mois | D20: mensuel | E20: =Parametres!$B$10 -> 219
A21: B3 | B21: Variante avec paiement annuel d'avance (2 mois offerts) | C21: Engagement 12 mois regle en une fois | D21: annuel | E21: =ROUND(Parametres!$B$9*10,-1) -> 1890
A22: B4 | B22: Intervention hors forfait de maintenance | C22: Evolution, incident imputable a un tiers, demande nouvelle | D22: a l'heure | E22: =Parametres!$B$11 -> 60
A24: BLOC C - CONDITIONS FINANCIERES
B25: Acompte a la commande | D25: =Parametres!$B$8 -> 0.4 | F25: =ROUND(F15*Parametres!$B$8,-1) -> 2120
B26: Solde a la signature du proces-verbal de recette | F26: =F15-F25 -> 3180
B27: Premiere annee : prestation initiale + 12 mois d'exploitation | F27: =F15+Parametres!$B$9*12 -> 7568
B28: Validite du devis | C28: 30 jours
B29: Delai indicatif de realisation | C29: 5 a 7 semaines a compter de la reception de l'acompte et des acces
B30: Garantie corrective | C30: 60 jours apres recette, sur le perimetre recette
B31: Clause de sortie apres la phase 1 | C31: Si la note de faisabilite conclut a l'impossibilite de recuperer automatiquement le fichier video depuis TikTok de maniere fiable, le client peut mettre fin au contrat sans indemnite. Seule la phase 1 (600 €) reste due, le solde de l'acompte est rembourse sous 15 jours.
B33: MENTION FISCALE OBLIGATOIRE | C33: Prestataire non assujetti a la TVA. Montants nets de taxe. Mention obligatoire : « TVA non applicable, article 293 B du CGI ». Ne jamais ecrire « HT ».

Sheet Scenarios
A1: Scenarios de prix et zone d'atterrissage
A3: Scenario | B3: Charge (j) | C3: Prix (€) | D3: Commentaire
A4: Provision pour aleas ramenee a 1,5 j | B4: =Kanban_Chiffrage!$F$50-0.5 -> 12.75 | C4: =B4*Parametres!$B$6 -> 5100 | D4: Marge de securite de 14 %, jugee insuffisante au vu de la dependance non officielle a TikTok
A5: Avec interface web d'administration | B5: =Kanban_Chiffrage!$F$50+1 -> 14.25 | C5: =B5*Parametres!$B$6 -> 5700 | D5: Ecarte : complexite et marge degradee pour un besoin non exprime
A6: Socle V1 retenu (sans interface web) | B6: =Kanban_Chiffrage!$F$50 -> 13.25 | C6: =Devis!F15 -> 5300 | D6: RECOMMANDE - sans interface web ni authentification a developper
A7: Cible initialement envisagee (3 500 €) | B7: =3500/Parametres!$B$6 -> 8.75 | C7: 3500 | D7: NON TENABLE au perimetre decrit : il faudrait supprimer une plateforme de destination ET la fiabilisation
A10: Rentabilite du projet sur 12 mois
A11: Chiffre d'affaires annee 1 (socle remise + 12 mois d'exploitation) | C11: =Devis!F15+Parametres!$B$9*12 -> 7568
A12: Couts externes annee 1 (serveur + passerelle) | C12: =-Parametres!$B$14*12 -> -900
A13: Marge brute annee 1 | C13: =C11+C12 -> 6668
A14: Nombre de jours vendus (socle) | C14: =Kanban_Chiffrage!$F$50 -> 13.25
A15: TJM effectif realise sur l'annee 1 | C15: =C13/C14 -> 503.24528 | D15: A comparer au TJM affiche. S'il est nettement inferieur, la remise ou l'abonnement sont mal calibres.
